LICENSE
MANIFEST.in
README.rst
setup.py
src/dictsdiff/__init__.py
src/dictsdiff/__main__.py
src/dictsdiff/cli.py
src/dictsdiff/conftest.py
src/dictsdiff/core.py
src/dictsdiff/loader.py
src/dictsdiff/utils.py
src/dictsdiff.egg-info/PKG-INFO
src/dictsdiff.egg-info/SOURCES.txt
src/dictsdiff.egg-info/dependency_links.txt
src/dictsdiff.egg-info/entry_points.txt
src/dictsdiff.egg-info/requires.txt
src/dictsdiff.egg-info/top_level.txt
src/dictsdiff/tests/__init__.py
src/dictsdiff/tests/test_cli.py
src/dictsdiff/tests/test_core.py
src/dictsdiff/tests/test_loader.py
src/dictsdiff/tests/test_utils.py