Metadata-Version: 1.1
Name: dictsdiff
Version: 0.1.1
Summary: CLI & Python API for comparing multiple dictionaries
Home-page: https://github.com/tkf/dictsdiff
Author: Takafumi Arakaki
Author-email: aka.tkf@gmail.com
License: BSD-2-Clause
Keywords: CLI,diff,JSON,YAML,Pickle
Platform: UNKNOWN
Classifier: Development Status :: 3 - Alpha
Classifier: License :: OSI Approved :: BSD License
Classifier: Programming Language :: Python :: 2.7
Classifier: Programming Language :: Python :: 3.6
Classifier: Topic :: Software Development
